{
	"configurations" : 
	[
		{
			"directories" : 
			[
				{
					"build" : ".",
					"jsonFile" : "directory-.-Debug-f5ebdc15457944623624.json",
					"minimumCMakeVersion" : 
					{
						"string" : "3.15"
					},
					"projectIndex" : 0,
					"source" : ".",
					"targetIndexes" : 
					[
						0,
						1
					]
				}
			],
			"name" : "Debug",
			"projects" : 
			[
				{
					"directoryIndexes" : 
					[
						0
					],
					"name" : "DDSHelloWorld",
					"targetIndexes" : 
					[
						0,
						1
					]
				}
			],
			"targets" : 
			[
				{
					"directoryIndex" : 0,
					"id" : "DDSHelloWorldPublisher::@6890427a1f51a3e7e1df",
					"jsonFile" : "target-DDSHelloWorldPublisher-Debug-d69101f25d2bd7304f1a.json",
					"name" : "DDSHelloWorldPublisher",
					"projectIndex" : 0
				},
				{
					"directoryIndex" : 0,
					"id" : "DDSHelloWorldSubscriber::@6890427a1f51a3e7e1df",
					"jsonFile" : "target-DDSHelloWorldSubscriber-Debug-655025ea8fab7a790a50.json",
					"name" : "DDSHelloWorldSubscriber",
					"projectIndex" : 0
				}
			]
		}
	],
	"kind" : "codemodel",
	"paths" : 
	{
		"build" : "/home/ubuntu/myhello/build",
		"source" : "/home/ubuntu/myhello"
	},
	"version" : 
	{
		"major" : 2,
		"minor" : 6
	}
}
